CHANGELOG.md
majormode/__init__.py
majormode/perseus/__init__.py
majormode/perseus/utils/__init__.py
majormode/perseus/utils/env.py
perseus_getenv_library-1.0.6.dist-info/LICENSE.md
perseus_getenv_library-1.0.6.dist-info/WHEEL
perseus_getenv_library-1.0.6.dist-info/METADATA
perseus_getenv_library-1.0.6.dist-info/RECORD
