Metadata-Version: 2.1
Name: perseus-getenv-library
Version: 1.0.6
Summary: Python library helper for reading environment variables
Home-page: https://github.com/majormode/perseus-getenv-python-library
License: SEE LICENSE IN <LICENSE.md>
Keywords: env,library,perseus
Author: Daniel CAUNE
Author-email: daniel.caune@gmail.com
Requires-Python: >=3.9
Classifier: Development Status :: 5 - Production/Stable
Classifier: License :: Other/Proprietary License
Classifier: Operating System :: OS Independent
Classifier: Programming Language :: Python
Classifier: Programming Language :: Python :: 3
Classifier: Programming Language :: Python :: 3.9
Classifier: Programming Language :: Python :: 3.10
Classifier: Programming Language :: Python :: 3.11
Classifier: Topic :: Software Development :: Libraries
Requires-Dist: perseus-core-library (>=1.20.4,<2.0.0)
Requires-Dist: python-dotenv (>=1.0,<2.0)
Project-URL: Repository, https://github.com/majormode/perseus-getenv-python-library
